{
  "type": "Feature",
  "properties": {
    "iso:country":"PT",
    "sg:address":"63, rue Rennequin",
    "sg:city":"Paris",
    "sg:classifiers":[
        {
            "category":"Professional",
            "subcategory":"Computer Services",
            "type":"Services"
        }
    ],
    "sg:postcode":"75017",
    "sg:tags":[
        "colombia"
    ],
    "sg:website":"http://www.bahu.com/",
    "wof:name":"Bahu",
    "wof:placetype":"venue"
},
  "geometry": {"coordinates":[2.297035,48.882434],"type":"Point"}
}