{
  "type": "Feature",
  "properties": {
    "iso:country":"PT",
    "sg:address":"R. Eng. Frederico Ulrich 2650",
    "sg:city":" Maia",
    "sg:classifiers":[
        {
            "category":"Professional",
            "subcategory":"Computer Services",
            "type":"Services"
        }
    ],
    "sg:postcode":"4470-605",
    "sg:website":"http://www.multiwavephotonics.com/",
    "wof:name":"Multiwave Photonics",
    "wof:placetype":"venue"
},
  "geometry": {"coordinates":[-8.6445243,41.2571688],"type":"Point"}
}