{
  "type": "Feature",
  "properties": {
    "iso:country":"PT",
    "sg:address":"Avenida Miguel Bombarda 123, 2\u00ba",
    "sg:city":"LISBOA",
    "sg:classifiers":[
        {
            "category":"Professional",
            "subcategory":"Computer Services",
            "type":"Services"
        }
    ],
    "sg:postcode":"1",
    "sg:tags":[
        "video",
        "image-aquisiition",
        "ocr",
        "scanner",
        "webcam",
        "broadcast",
        "software",
        "police",
        "euro"
    ],
    "sg:website":"http://www.capturix.com",
    "wof:name":"CAPTURIX",
    "wof:placetype":"venue"
},
  "geometry": {"coordinates":[-9.150734,38.7365154],"type":"Point"}
}