{
  "type": "Feature",
  "properties": {
    "iso:country":"PT",
    "sg:address":"Avenida de Roma n.\u00ba 129, 3\u00ba esquerdo",
    "sg:city":"Lisboa",
    "sg:classifiers":[
        {
            "category":"Professional",
            "subcategory":"Management & Consulting",
            "type":"Services"
        }
    ],
    "sg:postcode":"1700-346",
    "sg:tags":[
        "survs",
        "xsort",
        "design",
        "web",
        "card-sorting",
        "surveys"
    ],
    "sg:website":"http://www.enoughpepper.com",
    "wof:name":"Enough Pepper",
    "wof:placetype":"venue"
},
  "geometry": {"coordinates":[-9.1427493,38.7509471],"type":"Point"}
}