{
  "type": "Feature",
  "properties": {
    "iso:country":"PT",
    "sg:address":"Praceta Guilherme Gomes Fernandes N. 33 - 2\u00ba Direito",
    "sg:city":"Porto",
    "sg:classifiers":[
        {
            "category":"Professional",
            "subcategory":"Computer Services",
            "type":"Services"
        }
    ],
    "sg:postcode":"4050 - Porto",
    "sg:tags":[
        "ria",
        "web2-0",
        "web-applications",
        "social-platform"
    ],
    "sg:website":"http://www.ideavity.com",
    "wof:name":"Ideavity",
    "wof:placetype":"venue"
},
  "geometry": {"coordinates":[-8.614826,41.147536],"type":"Point"}
}